generalutils/__init__.py
generalutils/constants.py
generalutils/guard.py
generalutils-0.1.6.dist-info/AUTHORS.rst
generalutils-0.1.6.dist-info/METADATA
generalutils-0.1.6.dist-info/WHEEL
generalutils-0.1.6.dist-info/top_level.txt
generalutils-0.1.6.dist-info/RECORD
